{"otherData": {},"traceEvents":[{"cat":"function","dur":0,"name":"void __cdecl Strike::Renderer2D::Shutdown(void)","ph":"X","pid":0,"tid":2102351298,"ts":54648685196},{"cat":"function","dur":212,"name":"__cdecl Strike::Application::~Application(void)","ph":"X","pid":0,"tid":2102351298,"ts":54648685194},{"cat":"function","dur":82545,"name":"void __cdecl Strike::WindowsWindow::Shutdown(void)","ph":"X","pid":0,"tid":2102351298,"ts":54648685537},{"cat":"function","dur":82901,"name":"__cdecl Strike::WindowsWindow::~WindowsWindow(void)","ph":"X","pid":0,"tid":2102351298,"ts":54648685536}]}